Workbook

Sheet Mandate Summary
A1: MANDATE SUMMARY
A3: DEAL
A4: Property name | C4: Mandate ref
A5: Address | C5: Sector / asset type
A6: Client / vendor | C6: Tenure
A7: Sale structure (asset / share) | C7: VAT position (OTT / TOGC)
A8: MANDATE TERMS
A9: Mandate type | C9: Instruction date
A10: Agent / surveyor | C10: Fee basis
A11: Sending email account | C11: Abort fee
A12: Process type | C12: Send mode (auto / draft)
A13: Quoting price | C13: Target NIY
A14: KEY DATES
A15: Launch date | C15: Round 1 process letter
A16: Round 2 (best & final) | C16: Preferred bidder selected
A17: Heads of Terms agreed | C17: Target exchange
A18: Target completion | C18: Actual completion
A20: LIVE STATUS (auto-calculated)
A21: Buyers on list | B21: =COUNTA('Buyer Pipeline'!A4:A203) -> 0 | C21: NDAs issued | D21: =COUNTIF('Buyer Pipeline'!E4:E203,"Sent")+COUNTIF('Buyer Pipeline'!E4:E203,"Signed") -> 0
A22: NDAs signed | B22: =COUNTIF('Buyer Pipeline'!E4:E203,"Signed") -> 0 | C22: Buyers qualified (AML + PoF) | D22: =COUNTIFS('Buyer Pipeline'!J4:J203,"Clear",'Buyer Pipeline'!K4:K203,"Verified") -> 0
A23: Round 1 bids received | B23: =COUNTIF('Buyer Pipeline'!L4:L203,"Received") -> 0 | C23: Round 2 bids received | D23: =COUNTIF('Buyer Pipeline'!M4:M203,"Received") -> 0
A24: Round 3 bids received | B24: =COUNTIF('Buyer Pipeline'!N4:N203,"Received") -> 0 | C24: Highest offer (any round) | D24: =MAX('Bid Log'!B4:D203) -> 0
A25: Tasks outstanding | B25: =COUNTIF('Task Checklist'!D4:D200,"Not started")+COUNTIF('Task Checklist'!D4:D200,"In progress") -> 45 | C25: Current stage
A27: Counts pull live from the other tabs and update on recalculation.

Sheet Task Checklist
A1: TASK CHECKLIST (full sale lifecycle)
A3: Phase | B3: Task | C3: Owner | D3: Status | E3: Due date | F3: Date done | G3: Automated by
A4: 1. Mandate & setup | B4: Agree and sign agency / sale mandate | C4: Agent | D4: Not started | G4: onboard-mandate
A5: 1. Mandate & setup | B5: Confirm fee basis, abort fee, marketing budget | C5: Agent | D5: Not started | G5: onboard-mandate
A6: 1. Mandate & setup | B6: Confirm sale structure (asset vs share / SPV) | C6: Agent | D6: Not started | G6: onboard-mandate
A7: 1. Mandate & setup | B7: Run AML / KYC on vendor and beneficial owners | C7: Agent | D7: Not started | G7: onboard-mandate
A8: 1. Mandate & setup | B8: Confirm VAT position (OTT / TOGC) with client | C8: Agent | D8: Not started | G8: onboard-mandate
A9: 1. Mandate & setup | B9: Agree process type and timetable | C9: Agent | D9: Not started | G9: onboard-mandate
A10: 1. Mandate & setup | B10: Create deal folder, tracker and schedules | C10: Agent | D10: Not started | G10: setup-deal
A11: 2. Information & data room | B11: Collect title documents | C11: Agent | D11: Not started | G11: build-dataroom
A12: 2. Information & data room | B12: Collect leases, licences, deeds of variation | C12: Agent | D12: Not started | G12: build-dataroom
A13: 2. Information & data room | B13: Compile and verify tenancy schedule / rent roll | C13: Agent | D13: Not started | G13: build-dataroom
A14: 2. Information & data room | B14: Gather service charge budgets and accounts | C14: Agent | D14: Not started | G14: build-dataroom
A15: 2. Information & data room | B15: Obtain EPC(s) and confirm validity | C15: Agent | D15: Not started | G15: build-dataroom
... A48: 7. Reporting & close | B48: Issue final closing report to client | C48: Agent | D48: Not started | G48: client-report

Sheet Information & Data Room
A1: INFORMATION & DATA ROOM CHECKLIST
A3: Category | B3: Document | C3: Received | D3: In data room | E3: Date | F3: Notes
A4: Title | B4: Official copies of register and title plan | C4: No | D4: No
A5: Title | B5: Filed documents / restrictive covenants | C5: No | D5: No
A6: Leasing | B6: Leases, underleases and counterparts | C6: No | D6: No
A7: Leasing | B7: Licences and deeds of variation / side letters | C7: No | D7: No
A8: Leasing | B8: Tenancy schedule / rent roll (verified) | C8: No | D8: No
A9: Leasing | B9: Rent deposit deeds and AGAs / guarantees | C9: No | D9: No
A10: Financial | B10: Service charge budgets and reconciled accounts | C10: No | D10: No
A11: Financial | B11: Arrears report and rent receipts | C11: No | D11: No
A12: Compliance | B12: EPC certificate(s) | C12: No | D12: No
A13: Compliance | B13: Asbestos register / survey | C13: No | D13: No
A14: Compliance | B14: Fire risk assessment | C14: No | D14: No
A15: Compliance | B15: Condition / structural / M&E surveys | C15: No | D15: No
... A21: Diligence | B21: Replies to standard pre-contract enquiries (CPSE) | C21: No | D21: No

Sheet Buyer Pipeline
A1: BUYER PIPELINE
A3: Buyer | B3: Company | C3: Contact email | D3: Enquiry date | E3: NDA status | F3: NDA sent | G3: Last chase | H3: Chase count | I3: NDA signed | J3: AML/KYC | K3: Proof of funds | L3: R1 bid | M3: R2 bid | N3: R3 bid | O3: Notes

Sheet Bid Log
A1: BID COMPARISON
A2: (property): Round 1 bid comparison Prepared 07 Jun 2026
A3: Bidder | B3: R1 price | C3: R2 price | D3: R3 price | E3: Chg R1>R2 | F3: Chg R2>R3 | G3: Latest offer | H3: R1 NIY | I3: R2 NIY | J3: R3 NIY | K3: Movement | L3: Conditions (latest) | M3: Completion (latest) | N3: Funding / PoF | O3: Notes
E4: =IF(AND(B4<>"",C4<>""),C4-B4,"") | F4: =IF(AND(C4<>"",D4<>""),D4-C4,"") | G4: =IF(D4<>"",D4,IF(C4<>"",C4,IF(B4<>"",B4,"")))
E5: =IF(AND(B5<>"",C5<>""),C5-B5,"") | F5: =IF(AND(C5<>"",D5<>""),D5-C5,"") | G5: =IF(D5<>"",D5,IF(C5<>"",C5,IF(B5<>"",B5,"")))
E6: =IF(AND(B6<>"",C6<>""),C6-B6,"") | F6: =IF(AND(C6<>"",D6<>""),D6-C6,"") | G6: =IF(D6<>"",D6,IF(C6<>"",C6,IF(B6<>"",B6,"")))
E7: =IF(AND(B7<>"",C7<>""),C7-B7,"") | F7: =IF(AND(C7<>"",D7<>""),D7-C7,"") | G7: =IF(D7<>"",D7,IF(C7<>"",C7,IF(B7<>"",B7,"")))
E8: =IF(AND(B8<>"",C8<>""),C8-B8,"") | F8: =IF(AND(C8<>"",D8<>""),D8-C8,"") | G8: =IF(D8<>"",D8,IF(C8<>"",C8,IF(B8<>"",B8,"")))
E9: =IF(AND(B9<>"",C9<>""),C9-B9,"") | F9: =IF(AND(C9<>"",D9<>""),D9-C9,"") | G9: =IF(D9<>"",D9,IF(C9<>"",C9,IF(B9<>"",B9,"")))
E10: =IF(AND(B10<>"",C10<>""),C10-B10,"") | F10: =IF(AND(C10<>"",D10<>""),D10-C10,"") | G10: =IF(D10<>"",D10,IF(C10<>"",C10,IF(B10<>"",B10,"")))
E11: =IF(AND(B11<>"",C11<>""),C11-B11,"") | F11: =IF(AND(C11<>"",D11<>""),D11-C11,"") | G11: =IF(D11<>"",D11,IF(C11<>"",C11,IF(B11<>"",B11,"")))
A13: Movement: Improved / Held / Reduced compares a bidder's latest round with their previous round. Withdrawn = bid in an earlier round, none in the current round. New = first bid after round 1.
A14: To send to the client, select rows 1 to 11 and copy into the report. Figures are exclusive of VAT and costs.

Sheet Legal & Completion
A1: LEGAL & COMPLETION MILESTONES
A3: Milestone | B3: Responsible | C3: Status | D3: Target date | E3: Actual date | F3: Notes
A4: Preferred bidder confirmed | C4: Not started
A5: Heads of Terms agreed and circulated | C5: Not started
A6: Exclusivity / lockout in place | C6: Not started
A7: Vendor solicitors instructed | C7: Not started
A8: Contract pack issued to buyer solicitors | C8: Not started
A9: CPSE replies provided | C9: Not started
A10: Buyer searches submitted | C10: Not started
A11: Pre-contract enquiries answered | C11: Not started
A12: Buyer board / IC approval confirmed | C12: Not started
A13: Buyer funding confirmed | C13: Not started
A14: Contract approved / engrossed | C14: Not started
A15: Exchange of contracts | C15: Not started
... A20: Managing agent handover | C20: Not started

Sheet Client Reporting
A1: CLIENT REPORTING LOG
A3: Date | B3: Report type | C3: Period covered | D3: Sent to | E3: Method | F3: Summary / notes
